devopscodegen_common/chains/__init__.py
devopscodegen_common/chains/middleware_chain.py
devopscodegen_common/languages/__init__.py
devopscodegen_common/languages/language.py
devopscodegen_common/manifests/__init__.py
devopscodegen_common/manifests/dependency_manifest.py
devopscodegen_common/output_parsers/__init__.py
devopscodegen_common/output_parsers/devopscodegen_output_parser.py
devopscodegen_common/repositories/__init__.py
devopscodegen_common/repositories/code_repository.py
devopscodegen_common/repositories/git_source_code_repository.py
devopscodegen_common/repositories/repository.py
devopscodegen_common/repositories/source_code_repository.py
devopscodegen_common/repositories/tests/git_source_code_repository_test.py
devopscodegen_common/templates/middlewares/java/apache_maven/middlewares.txt
devopscodegen_common/templates/middlewares/python/poetry/middlewares.txt
devopscodegen_common/tools/__init__.py
devopscodegen_common/tools/dependency_management_tool.py
devopscodegen_common-1.20240710.8.dist-info/LICENSE
devopscodegen_common-1.20240710.8.dist-info/METADATA
devopscodegen_common-1.20240710.8.dist-info/WHEEL
devopscodegen_common-1.20240710.8.dist-info/RECORD
